sidepanel/__init__.py
sidepanel/_version.py
sidepanel/sidecore.py
sidepanel/sideoutput.py
sidepanel/sidepanel.py
sidepanel-0.4.4.dist-info/LICENSE.txt
sidepanel-0.4.4.dist-info/METADATA
sidepanel-0.4.4.dist-info/WHEEL
sidepanel-0.4.4.dist-info/top_level.txt
sidepanel-0.4.4.dist-info/RECORD
