Metadata-Version: 2.1
Name: sidepanel
Version: 0.4.4
Summary: Sidepanel extension for Jupyter
Home-page: https://github.com/yarden-livnat/sidepanel
Author: Yarden Livnat
Author-email: yarden@sci.utah.edu
License: BSD
Keywords: Interactive,JupyterLab
Platform: Linux
Platform: Mac OS X
Platform: Windows
Classifier: Intended Audience :: Developers
Classifier: Intended Audience :: Science/Research
Classifier: License :: OSI Approved :: BSD License
Classifier: Programming Language :: Python :: 3.7
Classifier: Framework :: Jupyter
Requires-Dist: ipywidgets (>=7.4.2)
Requires-Dist: traitlets (>=4.3.1)
